phytorchx/__init__.py
phytorchx/_version.py
phytorchx/_version.pyi
phytorchx/broadcast.py
phytorchx-0.3.1.dist-info/LICENSE.txt
phytorchx-0.3.1.dist-info/METADATA
phytorchx-0.3.1.dist-info/WHEEL
phytorchx-0.3.1.dist-info/top_level.txt
phytorchx-0.3.1.dist-info/RECORD
